flaskr/__about__.py
flaskr/__init__.py
flaskr/auth.py
flaskr/blog.py
flaskr/bp_navbar.py
flaskr/config_app.py
flaskr/db.py
flaskr/my_globals.py
flaskr/my_logging.py
flaskr/my_test.py
flaskr/my_thread3.py
flaskr/schema.sql
flaskr/hw/__init__.py
flaskr/hw/adc.py
flaskr/hw/bme280.py
flaskr/hw/cpu.py
flaskr/hw/fan.py
flaskr/hw/hw_base.py
flaskr/hw/ioex.py
flaskr/hw/keypad.py
flaskr/hw/lcd.py
flaskr/hw/led.py
flaskr/hw/ledcolor.py
flaskr/hw/modem.py
flaskr/hw/uart.py
flaskr/hw/wdn400s.py
flaskr/static/style.css
flaskr/static/css/bootstrap.min.css
flaskr/static/css/bootstrap.min.css.map
flaskr/static/css/dashboard.css
flaskr/static/css/navbar-top-fixed.css
flaskr/static/css/xxx-bootstrap.rtl.min.css
flaskr/static/css/xxx-bootstrap.rtl.min.css.map
flaskr/static/js/bootstrap.bundle.min.js
flaskr/static/js/bootstrap.bundle.min.js.map
flaskr/static/js/draw_chart.js
flaskr/templates/base.html
flaskr/templates/base_navbar.html
flaskr/templates/assets/brand/bootstrap-logo-white.svg
flaskr/templates/assets/brand/bootstrap-logo.svg
flaskr/templates/auth/login.html
flaskr/templates/auth/register.html
flaskr/templates/blog/create.html
flaskr/templates/blog/index.html
flaskr/templates/blog/update.html
flaskr/templates/dashboard/index.html
flaskr/templates/navbar/chart.html
flaskr/templates/navbar/chart.html.bak
flaskr/templates/navbar/config-test.html
flaskr/templates/navbar/config.html
flaskr/templates/navbar/config.html.bak
flaskr/templates/navbar/hello.html
flaskr/templates/navbar/index.html
flaskr/templates/navbar/navbar-top-fixed.css
flaskr/templates/navbar/status.html
naro_laser-0.1.2.dist-info/METADATA
naro_laser-0.1.2.dist-info/WHEEL
naro_laser-0.1.2.dist-info/top_level.txt
naro_laser-0.1.2.dist-info/RECORD
