Metadata-Version: 2.1
Name: naro-laser
Version: 0.1.2
Summary: A small example package
Home-page: UNKNOWN
Author: nash
Author-email: nash403@gmail.com
License: UNKNOWN
Platform: UNKNOWN
Classifier: Programming Language :: Python :: 3
Classifier: License :: OSI Approved :: MIT License
Classifier: Operating System :: OS Independent
Requires-Dist: flask
